mu0_reg16.v
// MU0 16 bit register design - behavioural style
// P W Nutter (based on a design by Jeff Pepper)
// Date 20/8/2021
//

// Do not touch the following line it is required for simulation
`timescale 1ns/100ps

// for simulation purposes, do not delete
`default_nettype none

// module header
module mu0_reg16(input  wire        Clk,
	             input  wire        Reset,
			     input  wire        En,
			     input  wire [15:0] D,
			     output reg  [15:0] Q);

// behavioural code - clock driven
always @ (posedge Clk, posedge Reset)
begin
    case(Reset)
		1'b1: Q <= 16'h0000; //if reset high, clear reg
		1'b0: if (En)
			 Q <= D;
		      else Q <= Q;
		default: Q <= 16'h0000;
    endcase
end
endmodule

// for simulation purposes, do not delete
`default_nettype wire

mu0_reg16_tb.v
// MU0 16 bit register testbench
// P W Nutter (based on a design by Jeff Pepper)
// Date 20/8/2021
//

// Do not touch the following line it is required for simulation
`timescale 1ns/100ps

// module header
module mu0_reg16_tb();

// Define any internal connections
reg Clk;
reg Reset;
reg En;
reg[15:0] D;
wire[15:0] Q;


// Instantiate mu0_reg16 as dut (device under test)
mu0_reg16 dut(Clk, Reset, En, D, Q);


// Set up the clock
// the following initial block initialises the clock
initial Clk = 0;

// the following always block creates the clock signal
always
 begin
    #50
    Clk = ~Clk;     //Inverts the Clock
 end

// Test vectors
initial
begin
  D = 16'hAAAA;
	#0 Reset = 1'b1; En = 1'b1; // check if D is not loaded since Reset is high (even though En is high)
	#200 Reset = 1'b0;
  D = 16'hBBBB;
	#200 Reset = 1'b0; En = 1'b0; // check if new value of D not loaded since En is low
	#200 Reset = 1'b0; En = 1'b1;
	#275 Reset = 1'b1;  // Test to check is Reset is asynchronous
	#125 Reset = 1'b0;
	#200 En = 1'b0;
	#200 Reset = 1'b1; // Checking if Reset overwrites data even if En is low
  #100 $finish;      // end the simulation
end

// Save results as VCD file
// Do not change
initial
 begin
  $dumpfile("mu0_reg16_tb_results.vcd");  // Save simulation waveforms in this file
  $dumpvars; // Capture all simulation waveforms
 end

endmodule

mu0_reg16_tb_results.vcd
$date
	Tue Dec  7 20:31:50 2021
$end
$version
	Icarus Verilog
$end
$timescale
	100ps
$end
$scope module mu0_reg16_tb $end
$var wire 16 ! Q [15:0] $end
$var reg 1 " Clk $end
$var reg 16 # D [15:0] $end
$var reg 1 $ En $end
$var reg 1 % Reset $end
$scope module dut $end
$var wire 1 " Clk $end
$var wire 16 & D [15:0] $end
$var wire 1 $ En $end
$var wire 1 % Reset $end
$var reg 16 ' Q [15:0] $end
$upscope $end
$upscope $end
$enddefinitions $end
#0
$dumpvars
b0 '
b1010101010101010 &
1%
1$
b1010101010101010 #
0"
b0 !
$end
#500
1"
#1000
0"
#1500
1"
#2000
0"
b1011101110111011 #
b1011101110111011 &
0%
#2500
b1011101110111011 !
b1011101110111011 '
1"
#3000
0"
#3500
1"
#4000
0"
0$
#4500
1"
#5000
0"
#5500
1"
#6000
0"
1$
#6500
1"
#7000
0"
#7500
1"
#8000
0"
#8500
1"
#8750
b0 !
b0 '
1%
#9000
0"
#9500
1"
#10000
0"
0%
#10500
b1011101110111011 !
b1011101110111011 '
1"
#11000
0"
#11500
1"
#12000
0"
0$
#12500
1"
#13000
0"
#13500
1"
#14000
b0 !
b0 '
0"
1%
