mu0_memory.v
// MU0 memory
// P W Nutter (based on a design by Jeff Pepper)
// Date 20/8/2021

// Single port memory module
// Address range 0 to 12'hEFF is memory/ram
// Uses a Synchronous RAM on a negedge clock, to fool processor into think its just a RAM

// Do not touch the following line it is required for simulation 
`timescale 1ns/100ps

// for simulation purposes, do not delete
`default_nettype none

`define MEM_SIZE   12'hEFF // Size of RAM

// module definition

module mu0_memory(input  wire        Clk, 
	              input  wire        Wr, 
				  input  wire        Rd, 
				  input  wire [11:0] Addr, 
				  input  wire [15:0] Data_in, 
				  output reg  [15:0] Data_out);


reg [15:0] mem [12'h000:`MEM_SIZE];	// memory array

initial
$readmemh("MU0_test.mem", mem); // load default MU0 test program


// RAM
always @ (negedge Clk) // Done to make SRAM look like asynchronous RAM, makes simulation work
 begin
  if(Wr) mem[Addr] <= Data_in;  // Write cpu data to ram
  if(Rd) Data_out <= mem[Addr];  // CPU reads from ram
 end
 
 endmodule

// for simulation purposes, do not delete
`default_nettype wire

mu0_control.v
// MU0 control design - behavioural style
// P W Nutter (based on a design by Jeff Pepper)
// Date 2/9/2020
// 

// Do not touch the following line it is required for simulation 
`timescale 1ns/100ps

// for simulation purposes, do not delete
`default_nettype none

// module definition

module mu0_control(input  wire         Clk,      // System clock
                   input  wire         Reset,    // System reset
                   input  wire  [3:0]  F,        // Bits [15:12] of the IR
                   input  wire         N,        // Negative flag
                   input  wire         Z,        // Zero flag
                   output wire          fetch,    // Used for debug
                   output wire          PC_En,    // Update PC
                   output wire          IR_En,    // Update IR
                   output wire          Acc_En,   // Update Acc
                   output wire          X_sel,    // Data Out mux(X port on ALU) 0 for Acc, 1 for PC
                   output wire          Y_sel,    // mux, Y port on ALU, 0 for Data In, 1 for Instr 
                   output wire          Addr_sel, // mux, 0 for PC, 1 for IR
                   output wire   [1:0]  M,        // ALU op, 0) Y, 1) X+Y, 2) X+1, 3) X-Y
                   output wire          Rd,       // Memory read
                   output wire          Wr,       // Memory write
                   output wire          Halted);  // MU0 stopped




wire state, not_Clk, not_state, not_Halted, t1, t2, t3, b1, b2, b3, s, not_s;
wire nF0, nF1, nF2, lda, sta, add, sub, jmp, jge, jne, j1, j2, nZ, nN;

not gate1 (fetch, state);
not gate2 (nF0, F[0]);
not gate3 (nF1, F[1]);
not gate4 (nF2, F[2]);

and gate5  (Halted, F[2], F[1], F[0], state);
and gate6  (jne, F[2], F[1], nF0, state);
and gate7  (jge, F[2], nF1, F[0], state);
and gate8  (jmp, F[2], nF1, nF0, state);
and gate9  (sub, nF2, F[1], F[0], state);
and gate10 (add, nF2, F[1], nF0, state);
and gate11 (sta, nF2, nF1, F[0], state);
and gate12 (lda, nF2, nF1, nF0, state);


buf gate13 (Y_sel, F[2]);
buf gate14 (IR_En, fetch);
buf gate15 (X_sel, fetch);
buf gate16 (Addr_sel, state);


not gate17 (nZ, Z);
not gate18 (nN, N);
and gate19 (j1, jne, nZ);
and gate20 (j2, jge, nN);
or  gate21 (PC_En, fetch, jmp, j1, j2);

or gate22 (M[1], sub, fetch);
or gate23 (M[0], add, sub);

buf gate24 (Wr, sta);

or gate25 (Rd, lda, add, sub, fetch);
or gate26 (Acc_En, lda, add, sub);
	       
not  gate27 (not_Clk, Clk);
not  gate28 (not_Halted, Halted);

or   gate29 (t1, not_state, Halted);
and  gate30 (t2, not_Clk, t1);
nor  gate31 (s, t2, not_s);
and  gate32 (t3, s, Clk);
nor  gate33 (state, t3, not_state, Reset);

or   gate34 (b1, state, not_Halted);
and  gate35 (b2, not_Clk, state);
nor  gate36 (not_s, b2, s, Reset);
and  gate37 (b3, not_s, Clk);
nor  gate38 (not_state, b3, state);


endmodule 

// for simulation purposes, do not delete
`default_nettype wire

mu0_flags.v
// MU0 flags design - behavioural style
// P W Nutter (based on a design by Jeff Pepper)
// Date 20/8/2021
// 

// Do not touch the following line it is required for simulation 
`timescale 1ns/100ps

// for simulation purposes, do not delete
`default_nettype none

// module definition

module mu0_flags(input  wire [15:0]  Acc, 
	             output reg          N, 
				 output reg          Z);

// Combinatorial logic

always @(*)
 begin
   Z = ~|Acc;     // When Acc equals 0, Zero flag is set
   N = Acc[15];   // When negative bit of Acc is set, Negative flag is set
 end

endmodule 

// for simulation purposes, do not delete
`default_nettype wire

mu0_alu.v
// MU0 ALU design 
// P W Nutter (based on a design by Jeff Pepper)
// Date 2/9/2020
// 

// Do not touch the following line it is required for simulation 
`timescale 1ns/100ps

// for simulation purposes, do not delete
`default_nettype none

// module header

module mu0_alu(input  wire [15:0]  X, 
               input  wire [15:0]  Y, 
               input  wire [1:0]   M, 
               output wire  [15:0]  Q);

// gate level description
wire [15:0] a, b, axorb, ab, cin_axorb, cout;
wire [1:0] not_M;
wire Xone_two_three;
wire [15:0] not_Y, Yzero_one, Ythree;



not  gate1 [1:0] (not_M, M);


or   gate2        (Xone_two_three, M[1], M[0]);
and  gate3 [15:0] (a, Xone_two_three, X);


not gate4 [15:0] (not_Y, Y);
and gate5 [15:0] (Yzero_one, not_M[1], Y);
and gate6 [15:0] (Ythree, M[1], M[0], not_Y);
or  gate7 [15:0] (b, Yzero_one, Ythree);

xor gate8 [15:0] (axorb, a, b);    
xor gate9 [15:0] (Q, {cout[14:0], M[1]}, axorb);
and gate10 [15:0] (ab, a, b);
and gate11 [15:0] (cin_axorb,  {cout[14:0], M[1]}, axorb); 
or  gate12 [15:0] (cout, cin_axorb, ab);


endmodule 

// for simulation purposes, do not delete
`default_nettype wire

mu0_mux12.v
// MU0 12 bit, 2 to 1 MUX design - behavioural style
// P W Nutter (based on a design by Jeff Pepper)
// Date 20/8/2021
//

// Do not touch the following line it is required for simulation
`timescale 1ns/100ps

// for simulation purposes, do not delete
`default_nettype none


module mu0_mux12(input  wire [11:0] A,
	             input  wire [11:0] B,
			     input  wire        S,
			     output reg  [11:0] Q);


// Combinatorial logic for 2to1 multiplexor
// S is select, A channel0, B channel1
always @ (*)
begin
	if (S == 1) Q = B;
	else if (S == 0) Q = A;
	else Q = 12'hxxx;
end
endmodule

// for simulation purposes, do not delete
`default_nettype wire

mu0_mux16.v
// MU0 16 bit, 2 to 1 MUX design - behavioural style
// P W Nutter (based on a design by Jeff Pepper)
// Date 20/8/2021
//

// Do not touch the following line it is required for simulation
`timescale 1ns/100ps

// for simulation purposes, do not delete
`default_nettype none

// module definition
module mu0_mux16(input  wire  [15:0] A,
	             input  wire  [15:0] B,
			     input  wire         S,
			     output reg  [15:0]  Q);


// Combinatorial logic for 2to1 multiplexor
// S is select, A channel0, B channel1
always @ (*)
begin
	if (S == 1) Q = B;
	else if (S == 0) Q = A;
	else Q = 16'hxxxx;
end
endmodule


// for simulation purposes, do not delete
`default_nettype wire

mu0_reg16.v
// MU0 16 bit register design - behavioural style
// P W Nutter (based on a design by Jeff Pepper)
// Date 20/8/2021
//

// Do not touch the following line it is required for simulation
`timescale 1ns/100ps

// for simulation purposes, do not delete
`default_nettype none

// module header
module mu0_reg16(input  wire        Clk,
	             input  wire        Reset,
			     input  wire        En,
			     input  wire [15:0] D,
			     output reg  [15:0] Q);

// behavioural code - clock driven
always @ (posedge Clk, posedge Reset)
begin
    case(Reset)
		1'b1: Q <= 16'h0000; //if reset high, clear reg
		1'b0: if (En)
			 Q <= D;
		      else Q <= Q;
		default: Q <= 16'h0000;
    endcase
end
endmodule

// for simulation purposes, do not delete
`default_nettype wire

mu0_reg12.v
// MU0 12 bit register design - behavioural style
// P W Nutter (based on a design by Jeff Pepper)
// Date 20/8/2021
//

// Do not touch the following line it is required for simulation
`timescale 1ns/100ps

// for simulation purposes, do not delete
`default_nettype none

// module header
module mu0_reg12(input  wire        Clk,
	             input  wire        Reset,
			     input  wire        En,
			     input  wire [11:0] D,
			     output reg  [11:0] Q);

// behavioural code - clock driven
always @ (posedge Clk, posedge Reset)
begin
    case(Reset)
		1'b1: Q <= 12'h000; //if reset high, clear reg
		1'b0: if (En)
			 Q <= D;
		      else Q <= Q;
		default: Q <= 12'h000;
    endcase
end
endmodule

// for simulation purposes, do not delete
`default_nettype wire

mu0_datapath.v
// MU0 datapath design - structural style
// P W Nutter (based on a design by Jeff Pepper)
// Date 20/8/2021
//

// Do not touch the following line it is required for simulation
`timescale 1ns/100ps

// for simulation purposes, do not delete
`default_nettype none

module mu0_datapath(input  wire        Clk,
                    input  wire        Reset,
                    input  wire [15:0] Data_in,
					input  wire        X_sel,
					input  wire        Y_sel,
					input  wire        Addr_sel,
					input  wire        PC_En,
					input  wire        IR_En,
					input  wire        Acc_En,
					input  wire [1:0]  M,
                    output wire [3:0]  F,			// top 4 bits of the instruction
                    output wire [11:0] Address,
                    output wire [15:0] Data_out,
                    output wire        N,
					output wire        Z);


// Define internal signals using names from the datapath schematic
wire [15:0] ALU;
wire [15:0] X;
wire [15:0] Y;
wire [11:0] PC;
wire [15:0] Acc;
wire [15:0] IR;

// Instantiate Datapath components
//MU0 registers
mu0_reg12 PCReg (Clk, Reset, PC_En, ALU[11:0], PC[11:0]);
mu0_reg16 IRReg (Clk, Reset, IR_En, Data_in[15:0], IR[15:0]);
mu0_reg16 ACCReg (Clk, Reset, Acc_En, ALU[15:0], Acc[15:0]);

// MU0 multiplexors
mu0_mux16 YMux (Data_in[15:0], IR[15:0], Y_sel, Y[15:0]);
mu0_mux16 XMux (Acc[15:0], {4'b0000, PC[11:0]}, X_sel, X[15:0]);
mu0_mux12 AddrMux (PC[11:0], IR[11:0], Addr_sel, Address[11:0]);


// MU0 ALU
mu0_alu mu0_ALU (X[15:0], Y[15:0], M[1:0], ALU[15:0]);


// MU0 Flag generation
mu0_flags FLAGS (Acc[15:0], N, Z);


// The following connects X and Data_out together, there's no need for you to do so
// use X iwhen defining your datapath structure
buf DOUTBuf[15:0] (Data_out, X);
// Buffer added F is op 4 bits of the instruction
buf FBuf[3:0] (F, IR[15:12]);

endmodule

mu0.v
// MU0 design - structural style
// P W Nutter (based on a design by Jeff Pepper)
// Date 20/8/2021
// 

// Do not touch the following line it is required for simulation 
`timescale 1ns/100ps

// for simulation purposes, do not delete
`default_nettype none

module mu0(input  wire         Clk,
           input  wire         Reset,
           input  wire [15:0]  Data_in,
           output wire         Rd,
           output wire         Wr,
           output wire [11:0]  Addr,
           output wire [15:0]  Data_out,
           output wire         Halted);

// Internal flags
wire N;
wire Z;

// Define any internal signals
wire X_sel;
wire Y_sel;
wire Addr_sel;
wire PC_En;
wire IR_En;
wire Acc_En;
wire [1:0] M;
wire [3:0] F;
wire fetch;



//Instantiate Datapath
mu0_datapath DataPath (Clk, Reset, Data_in[15:0], X_sel, Y_sel, Addr_sel, PC_En, IR_En, Acc_En, M[1:0], F[3:0], Addr[11:0], Data_out[15:0], N, Z);

 
// Instantiate Control
mu0_control Control (Clk, Reset, F[3:0], N, Z, fetch, PC_En, IR_En, Acc_En, X_sel, Y_sel, Addr_sel, M[1:0], Rd, Wr, Halted);


endmodule 

// for simulation purposes, do not delete
`default_nettype wire

mu0_tb.v
// MU0 testbench
// P W Nutter (based on a design by Jeff Pepper)
// Date 20/8/2021
//

// Do not touch the following line it is required for simulation
`timescale 1ns/100ps

module mu0_tb();

// Define any internal connections
reg Reset;
reg Clk;
wire Rd;
wire Wr;
wire [15:0] Data_in;
wire [15:0] Data_out;
wire [11:0] Address;
wire Halted;


// mu0 as dut (device under test) and mu0_memory have been instantiated
// for you
mu0 dut(Clk, Reset, Data_in, Rd, Wr, Address, Data_out, Halted);
mu0_memory memory(Clk, Wr, Rd, Address, Data_out, Data_in);

//Set Up Clock
// the following initial block initialises the clock
initial Clk = 0;

// the following always block creates the clock signal
always
 begin
    #50
    Clk = ~Clk;     //Inverts the Clock
 end

// Perform a reset action of MU0
initial
begin
   #0 Reset = 1;
   #400 Reset = 0;
   #4100 $finish; // exit the simulation - could tie this to the Halted signal going high
end

// Save results as VCD file
// Do not change
initial
 begin
  $dumpfile("mu0_tb_results.vcd");  // Save simulation waveforms in this file
  $dumpvars; // Capture all simulation waveforms
 end

endmodule

mu0_tb_results.vcd
$date
	Wed Dec  8 12:22:40 2021
$end
$version
	Icarus Verilog
$end
$timescale
	100ps
$end
$scope module mu0_tb $end
$var wire 1 ! Wr $end
$var wire 1 " Rd $end
$var wire 1 # Halted $end
$var wire 16 $ Data_out [15:0] $end
$var wire 16 % Data_in [15:0] $end
$var wire 12 & Address [11:0] $end
$var reg 1 ' Clk $end
$var reg 1 ( Reset $end
$scope module dut $end
$var wire 1 ' Clk $end
$var wire 1 ( Reset $end
$var wire 1 ) fetch $end
$var wire 1 * Z $end
$var wire 1 + Y_sel $end
$var wire 1 , X_sel $end
$var wire 1 ! Wr $end
$var wire 1 " Rd $end
$var wire 1 - PC_En $end
$var wire 1 . N $end
$var wire 2 / M [1:0] $end
$var wire 1 0 IR_En $end
$var wire 1 # Halted $end
$var wire 4 1 F [3:0] $end
$var wire 16 2 Data_out [15:0] $end
$var wire 16 3 Data_in [15:0] $end
$var wire 1 4 Addr_sel $end
$var wire 12 5 Addr [11:0] $end
$var wire 1 6 Acc_En $end
$scope module Control $end
$var wire 1 6 Acc_En $end
$var wire 1 4 Addr_sel $end
$var wire 1 ' Clk $end
$var wire 1 # Halted $end
$var wire 1 0 IR_En $end
$var wire 1 - PC_En $end
$var wire 1 " Rd $end
$var wire 1 ( Reset $end
$var wire 1 ! Wr $end
$var wire 1 , X_sel $end
$var wire 1 + Y_sel $end
$var wire 1 7 add $end
$var wire 1 8 b1 $end
$var wire 1 9 b2 $end
$var wire 1 : b3 $end
$var wire 1 ) fetch $end
$var wire 1 ; j1 $end
$var wire 1 < j2 $end
$var wire 1 = jge $end
$var wire 1 > jmp $end
$var wire 1 ? jne $end
$var wire 1 @ lda $end
$var wire 1 A nF0 $end
$var wire 1 B nF1 $end
$var wire 1 C nF2 $end
$var wire 1 D nN $end
$var wire 1 E nZ $end
$var wire 1 F not_Clk $end
$var wire 1 G not_Halted $end
$var wire 1 H not_s $end
$var wire 1 I not_state $end
$var wire 1 J s $end
$var wire 1 K sta $end
$var wire 1 L state $end
$var wire 1 M sub $end
$var wire 1 N t1 $end
$var wire 1 O t2 $end
$var wire 1 P t3 $end
$var wire 1 * Z $end
$var wire 1 . N $end
$var wire 2 Q M [1:0] $end
$var wire 4 R F [3:0] $end
$upscope $end
$scope module DataPath $end
$var wire 1 6 Acc_En $end
$var wire 1 4 Addr_sel $end
$var wire 1 ' Clk $end
$var wire 16 S Data_out [15:0] $end
$var wire 4 T F [3:0] $end
$var wire 1 0 IR_En $end
$var wire 2 U M [1:0] $end
$var wire 1 - PC_En $end
$var wire 1 ( Reset $end
$var wire 1 , X_sel $end
$var wire 1 + Y_sel $end
$var wire 1 * Z $end
$var wire 16 V Y [15:0] $end
$var wire 16 W X [15:0] $end
$var wire 12 X PC [11:0] $end
$var wire 1 . N $end
$var wire 16 Y IR [15:0] $end
$var wire 16 Z Data_in [15:0] $end
$var wire 12 [ Address [11:0] $end
$var wire 16 \ Acc [15:0] $end
$var wire 16 ] ALU [15:0] $end
$scope module ACCReg $end
$var wire 1 ' Clk $end
$var wire 1 6 En $end
$var wire 1 ( Reset $end
$var wire 16 ^ D [15:0] $end
$var reg 16 _ Q [15:0] $end
$upscope $end
$scope module AddrMux $end
$var wire 12 ` B [11:0] $end
$var wire 1 4 S $end
$var wire 12 a A [11:0] $end
$var reg 12 b Q [11:0] $end
$upscope $end
$scope module FLAGS $end
$var wire 16 c Acc [15:0] $end
$var reg 1 . N $end
$var reg 1 * Z $end
$upscope $end
$scope module IRReg $end
$var wire 1 ' Clk $end
$var wire 1 0 En $end
$var wire 1 ( Reset $end
$var wire 16 d D [15:0] $end
$var reg 16 e Q [15:0] $end
$upscope $end
$scope module PCReg $end
$var wire 1 ' Clk $end
$var wire 12 f D [11:0] $end
$var wire 1 - En $end
$var wire 1 ( Reset $end
$var reg 12 g Q [11:0] $end
$upscope $end
$scope module XMux $end
$var wire 16 h A [15:0] $end
$var wire 16 i B [15:0] $end
$var wire 1 , S $end
$var reg 16 j Q [15:0] $end
$upscope $end
$scope module YMux $end
$var wire 16 k B [15:0] $end
$var wire 1 + S $end
$var wire 16 l A [15:0] $end
$var reg 16 m Q [15:0] $end
$upscope $end
$scope module mu0_ALU $end
$var wire 2 n M [1:0] $end
$var wire 16 o Q [15:0] $end
$var wire 16 p X [15:0] $end
$var wire 1 q Xone_two_three $end
$var wire 16 r Y [15:0] $end
$var wire 16 s Ythree [15:0] $end
$var wire 16 t Yzero_one [15:0] $end
$var wire 16 u a [15:0] $end
$var wire 16 v ab [15:0] $end
$var wire 16 w axorb [15:0] $end
$var wire 16 x b [15:0] $end
$var wire 16 y cin_axorb [15:0] $end
$var wire 16 z cout [15:0] $end
$var wire 2 { not_M [1:0] $end
$var wire 16 | not_Y [15:0] $end
$upscope $end
$upscope $end
$upscope $end
$scope module memory $end
$var wire 12 } Addr [11:0] $end
$var wire 1 ' Clk $end
$var wire 16 ~ Data_in [15:0] $end
$var wire 1 " Rd $end
$var wire 1 ! Wr $end
$var reg 16 !" Data_out [15:0] $end
$upscope $end
$upscope $end
$enddefinitions $end
#0
$dumpvars
bx !"
b0 ~
b0 }
bx |
b1 {
b0 z
b0 y
b0 x
b0 w
b0 v
b0 u
b0 t
b0 s
bx r
1q
b0 p
b1 o
b10 n
bx m
bx l
b0 k
b0 j
b0 i
b0 h
b0 g
b1 f
b0 e
bx d
b0 c
b0 b
b0 a
b0 `
b0 _
b1 ^
b1 ]
b0 \
b0 [
bx Z
b0 Y
b0 X
b0 W
bx V
b10 U
b0 T
b0 S
b0 R
b10 Q
0P
1O
1N
0M
0L
0K
0J
1I
0H
1G
1F
0E
1D
1C
1B
1A
0@
0?
0>
0=
0<
0;
0:
09
18
07
06
b0 5
04
bx 3
b0 2
b0 1
10
b10 /
0.
1-
1,
0+
1*
1)
1(
0'
b0 &
bx %
b0 $
0#
1"
0!
$end
#500
1P
1J
0O
0F
1'
#1000
b1110111111011101 |
b1000000100010 V
b1000000100010 m
b1000000100010 r
b1000000100010 %
b1000000100010 3
b1000000100010 Z
b1000000100010 d
b1000000100010 l
b1000000100010 !"
0J
1O
1F
0P
0'
#1500
1P
1J
0O
0F
1'
#2000
0J
1O
1F
0P
0'
#2500
1P
1J
0O
0F
1'
#3000
0J
1O
1F
0P
0'
#3500
1P
1J
0O
0F
1'
#4000
1H
0J
1O
1F
0P
0'
0(
#4500
0"
1!
1K
0A
b1 1
b1 R
b1 T
b100010 &
b100010 5
b100010 [
b100010 b
b100010 }
b100010 `
b1000000100010 Y
b1000000100010 e
b1000000100010 k
b1 i
b1 X
b1 a
b1 g
b1000000100010 w
b1000000100010 x
b1000000100010 t
b100010 f
0q
b1000000100010 ]
b1000000100010 ^
b1000000100010 o
b11 {
06
00
0,
0-
b0 /
b0 Q
b0 U
b0 n
14
0@
0)
1L
0N
0O
0I
0F
1:
1'
#5000
1J
0H
19
1F
0:
0'
#5500
b1 z
b1 y
b0 x
b1 w
b0 t
b10 f
b1 u
b1 $
b1 2
b1 S
b1 ~
1q
b10 ]
b10 ^
b10 o
b1 W
b1 j
b1 p
b1 {
1N
b1 &
b1 5
b1 [
b1 b
b1 }
0!
10
1,
1-
b10 /
b10 Q
b10 U
b10 n
1"
1I
04
0K
1)
09
0L
0F
1P
1'
#6000
b1111111111100011 |
b11100 V
b11100 m
b11100 r
b11100 %
b11100 3
b11100 Z
b11100 d
b11100 l
b11100 !"
1H
0J
1O
1F
0P
0'
#6500
16
1@
1A
b0 1
b0 R
b0 T
b11100 `
b11100 Y
b11100 e
b11100 k
b10 i
b10 X
b10 a
b10 g
b11100 x
b11100 w
b11100 t
b11100 f
b0 z
b0 u
b0 $
b0 2
b0 S
b0 ~
0q
b11100 ]
b11100 ^
b11100 o
b0 y
b0 W
b0 j
b0 p
b11 {
b11100 &
b11100 5
b11100 [
b11100 b
b11100 }
0!
00
0,
0-
b0 /
b0 Q
b0 U
b0 n
1"
14
0K
0)
1L
0N
0O
0I
0F
1:
1'
#7000
b0 f
b1000000000000000 ]
b1000000000000000 ^
b1000000000000000 o
b1000000000000000 w
b1000000000000000 x
b111111111111111 |
b1000000000000000 t
b1000000000000000 V
b1000000000000000 m
b1000000000000000 r
b1000000000000000 %
b1000000000000000 3
b1000000000000000 Z
b1000000000000000 d
b1000000000000000 l
b1000000000000000 !"
1J
0H
19
1F
0:
0'
#7500
0D
1E
1.
0*
b1000000000000000 \
b1000000000000000 _
b1000000000000000 c
b1000000000000000 h
b0 x
b10 w
b0 t
b11 f
b10 u
b10 $
b10 2
b10 S
b10 ~
1q
b11 ]
b11 ^
b11 o
b10 W
b10 j
b10 p
b1 {
1N
b10 &
b10 5
b10 [
b10 b
b10 }
06
10
1,
1-
b10 /
b10 Q
b10 U
b10 n
1I
04
0@
1)
09
0L
0F
1P
1'
#8000
b1110111111011100 |
b1000000100011 V
b1000000100011 m
b1000000100011 r
b1000000100011 %
b1000000100011 3
b1000000100011 Z
b1000000100011 d
b1000000100011 l
b1000000100011 !"
1H
0J
1O
1F
0P
0'
#8500
0"
1!
1K
0A
b1 1
b1 R
b1 T
b100011 `
b1000000100011 Y
b1000000100011 e
b1000000100011 k
b11 i
b11 X
b11 a
b11 g
b1000000100011 x
b1000000100011 w
b1000000100011 t
b100011 f
b0 u
b1000000000000000 $
b1000000000000000 2
b1000000000000000 S
b1000000000000000 ~
0q
b1000000100011 ]
b1000000100011 ^
b1000000100011 o
b1000000000000000 W
b1000000000000000 j
b1000000000000000 p
b11 {
b100011 &
b100011 5
b100011 [
b100011 b
b100011 }
06
00
0,
0-
b0 /
b0 Q
b0 U
b0 n
14
0@
0)
1L
0N
0O
0I
0F
1:
1'
#9000
1J
0H
19
1F
0:
0'
#9500
b0 x
b11 w
b0 v
b0 t
b100 f
b11 z
b11 u
b11 $
b11 2
b11 S
b11 ~
1q
b100 ]
b100 ^
b100 o
b11 y
b11 W
b11 j
b11 p
b1 {
1N
b11 &
b11 5
b11 [
b11 b
b11 }
0!
10
1,
1-
b10 /
b10 Q
b10 U
b10 n
1"
1I
04
0K
1)
09
0L
0F
1P
1'
#10000
b1101111111100011 |
b10000000011100 V
b10000000011100 m
b10000000011100 r
b10000000011100 %
b10000000011100 3
b10000000011100 Z
b10000000011100 d
b10000000011100 l
b10000000011100 !"
1H
0J
1O
1F
0P
0'
#10500
16
17
0B
1A
b10 1
b10 R
b10 T
b11100 `
b10000000011100 Y
b10000000011100 e
b10000000011100 k
b100 i
b100 X
b100 a
b100 g
b10000000011100 x
b1010000000011100 w
b10000000011100 t
b11100 f
b0 z
b1000000000000000 u
b1000000000000000 $
b1000000000000000 2
b1000000000000000 S
b1000000000000000 ~
1q
b1010000000011100 ]
b1010000000011100 ^
b1010000000011100 o
b0 y
b1000000000000000 W
b1000000000000000 j
b1000000000000000 p
b10 {
b11100 &
b11100 5
b11100 [
b11100 b
b11100 }
0!
00
0,
0-
b1 /
b1 Q
b1 U
b1 n
1"
14
0K
0)
1L
0N
0O
0I
0F
1:
1'
#11000
b0 f
b0 ]
b0 ^
b0 o
b1000000000000000 z
b0 w
b1000000000000000 v
b1000000000000000 x
b111111111111111 |
b1000000000000000 t
b1000000000000000 V
b1000000000000000 m
b1000000000000000 r
b1000000000000000 %
b1000000000000000 3
b1000000000000000 Z
b1000000000000000 d
b1000000000000000 l
b1000000000000000 !"
1J
0H
19
1F
0:
0'
#11500
1D
0E
0.
1*
b0 \
b0 _
b0 c
b0 h
b0 z
b0 x
b100 w
b0 v
b0 t
b101 f
b100 u
b100 $
b100 2
b100 S
b100 ~
b101 ]
b101 ^
b101 o
b100 W
b100 j
b100 p
b1 {
1N
b100 &
b100 5
b100 [
b100 b
b100 }
06
10
1,
1-
b10 /
b10 Q
b10 U
b10 n
1I
04
07
1)
09
0L
0F
1P
1'
#12000
b1110111111011011 |
b1000000100100 V
b1000000100100 m
b1000000100100 r
b1000000100100 %
b1000000100100 3
b1000000100100 Z
b1000000100100 d
b1000000100100 l
b1000000100100 !"
1H
0J
1O
1F
0P
0'
#12500
0q
1!
0"
1K
1B
0A
b1 1
b1 R
b1 T
b100100 `
b1000000100100 Y
b1000000100100 e
b1000000100100 k
b101 i
b101 X
b101 a
b101 g
b1000000100100 x
b1000000100100 w
b1000000100100 t
b100100 f
b0 u
b0 $
b0 2
b0 S
b0 ~
b1000000100100 ]
b1000000100100 ^
b1000000100100 o
b0 W
b0 j
b0 p
b11 {
b100100 &
b100100 5
b100100 [
b100100 b
b100100 }
06
00
0,
0-
b0 /
b0 Q
b0 U
b0 n
14
07
0)
1L
0N
0O
0I
0F
1:
1'
#13000
1J
0H
19
1F
0:
0'
#13500
b1 y
b1 z
b0 x
b101 w
b0 v
b0 t
b110 f
b101 u
b101 $
b101 2
b101 S
b101 ~
1q
b110 ]
b110 ^
b110 o
b101 W
b101 j
b101 p
b1 {
1N
b101 &
b101 5
b101 [
b101 b
b101 }
0!
10
1,
1-
b10 /
b10 Q
b10 U
b10 n
1"
1I
04
0K
1)
09
0L
0F
1P
1'
#14000
b1100111111100100 |
b11000000011011 V
b11000000011011 m
b11000000011011 r
b11000000011011 %
b11000000011011 3
b11000000011011 Z
b11000000011011 d
b11000000011011 l
b11000000011011 !"
1H
0J
1O
1F
0P
0'
#14500
b1100111111100100 s
16
1M
0B
b11 1
b11 R
b11 T
b11011 `
b11000000011011 Y
b11000000011011 e
b11000000011011 k
b110 i
b110 X
b110 a
b110 g
b1100111111100100 x
b1100111111100100 w
b0 t
b111111100101 f
b0 z
b0 u
b0 $
b0 2
b0 S
b0 ~
1q
b1100111111100101 ]
b1100111111100101 ^
b1100111111100101 o
b0 y
b0 W
b0 j
b0 p
b0 {
b11011 &
b11011 5
b11011 [
b11011 b
b11011 }
0!
00
0,
0-
b11 /
b11 Q
b11 U
b11 n
1"
14
0K
0)
1L
0N
0O
0I
0F
1:
1'
#15000
b111111111111 f
b1111111111111111 ]
b1111111111111111 ^
b1111111111111111 o
b1111111111111110 w
b1111111111111110 x
b1111111111111110 s
b1111111111111110 |
b1 V
b1 m
b1 r
b1 %
b1 3
b1 Z
b1 d
b1 l
b1 !"
1J
0H
19
1F
0:
0'
#15500
0D
1E
1.
0*
b1111111111111111 \
b1111111111111111 _
b1111111111111111 c
b1111111111111111 h
b0 y
b111 f
b111 ]
b111 ^
b111 o
b0 z
b0 x
b110 w
b0 v
b0 s
b110 u
b110 $
b110 2
b110 S
b110 ~
b1 {
b110 W
b110 j
b110 p
1N
b110 &
b110 5
b110 [
b110 b
b110 }
b10 /
b10 Q
b10 U
b10 n
06
10
1,
1-
1I
04
0M
1)
09
0L
0F
1P
1'
#16000
b1110111111011010 |
b1000000100101 V
b1000000100101 m
b1000000100101 r
b1000000100101 %
b1000000100101 3
b1000000100101 Z
b1000000100101 d
b1000000100101 l
b1000000100101 !"
1H
0J
1O
1F
0P
0'
#16500
b1000000100101 t
0q
1!
0"
1K
1B
b1 1
b1 R
b1 T
b100101 `
b1000000100101 Y
b1000000100101 e
b1000000100101 k
b111 i
b111 X
b111 a
b111 g
b100101 f
b0 z
b0 v
b1000000100101 ]
b1000000100101 ^
b1000000100101 o
b0 y
b1000000100101 x
b1000000100101 w
b0 s
b0 u
b1111111111111111 $
b1111111111111111 2
b1111111111111111 S
b1111111111111111 ~
b11 {
b1111111111111111 W
b1111111111111111 j
b1111111111111111 p
b100101 &
b100101 5
b100101 [
b100101 b
b100101 }
b0 /
b0 Q
b0 U
b0 n
06
00
0,
0-
14
0M
0)
1L
0N
0O
0I
0F
1:
1'
#17000
1J
0H
19
1F
0:
0'
#17500
b0 x
b111 w
b0 v
b0 t
b1000 f
b111 z
b111 u
b111 $
b111 2
b111 S
b111 ~
1q
b1000 ]
b1000 ^
b1000 o
b111 y
b111 W
b111 j
b111 p
b1 {
1N
b111 &
b111 5
b111 [
b111 b
b111 }
0!
10
1,
1-
b10 /
b10 Q
b10 U
b10 n
1"
1I
04
0K
1)
09
0L
0F
1P
1'
#18000
b1011111111110101 |
b100000000001010 V
b100000000001010 m
b100000000001010 r
b100000000001010 %
b100000000001010 3
b100000000001010 Z
b100000000001010 d
b100000000001010 l
b100000000001010 !"
1H
0J
1O
1F
0P
0'
#18500
1+
1>
0C
1A
b100 1
b100 R
b100 T
b1010 `
b100000000001010 Y
b100000000001010 e
b100000000001010 k
b1000 i
b1000 X
b1000 a
b1000 g
b100000000001010 x
b100000000001010 w
b100000000001010 t
b1010 f
b0 z
b0 u
b1111111111111111 $
b1111111111111111 2
b1111111111111111 S
b1111111111111111 ~
0q
b100000000001010 ]
b100000000001010 ^
b100000000001010 o
b0 y
b1111111111111111 W
b1111111111111111 j
b1111111111111111 p
b11 {
b1010 &
b1010 5
b1010 [
b1010 b
b1010 }
0!
00
0,
1-
b0 /
b0 Q
b0 U
b0 n
0"
14
0K
0)
1L
0N
0O
0I
0F
1:
1'
#19000
1J
0H
19
1F
0:
0'
#19500
b1010 i
b1010 X
b1010 a
b1010 g
b0 z
b0 x
b1010 w
b0 v
b0 t
b1011 f
b1010 u
b1010 $
b1010 2
b1010 S
b1010 ~
1q
b1011 ]
b1011 ^
b1011 o
b1010 W
b1010 j
b1010 p
b1 {
1N
b1010 &
b1010 5
b1010 [
b1010 b
b1010 }
10
1,
b10 /
b10 Q
b10 U
b10 n
1"
1I
04
0>
1)
09
0L
0F
1P
1'
#20000
b11011 %
b11011 3
b11011 Z
b11011 d
b11011 l
b11011 !"
1H
0J
1O
1F
0P
0'
